amdinfer/__init__.py
amdinfer/_amdinfer.cpython-38-x86_64-linux-gnu.so
amdinfer/pre_post/__init__.py
amdinfer/testing/__init__.py
amdinfer-0.4.0.dist-info/LICENSE
amdinfer-0.4.0.dist-info/top_level.txt
amdinfer-0.4.0.dist-info/WHEEL
amdinfer-0.4.0.dist-info/RECORD
amdinfer-0.4.0.dist-info/METADATA
amdinfer.libs/libprotobuf-8d3ee58c.so.3.21.12.0
amdinfer.libs/libgrpc++-6a8b5beb.so.1.51.1
amdinfer.libs/libaddress_sorting-b959368a.so.29.0.0
amdinfer.libs/libre2-19133eed.so.10.0.0
amdinfer.libs/libbrotlicommon-6f725040.so.1.0.9
amdinfer.libs/libcares-760ae175.so.2.6.0
amdinfer.libs/libgpr-b5ed05e8.so.29.0.0
amdinfer.libs/libdrogon-0ca02720.so.1.8.4
amdinfer.libs/libgrpc-47217f4f.so.29.0.0
amdinfer.libs/libfmt-1978bbdc.so.9.1.0
amdinfer.libs/libopencv_core4-ad50b8a4.so.4.7.0
amdinfer.libs/libbrotlienc-c2ab4635.so.1.0.9
amdinfer.libs/libjsoncpp-457606a9.so.1.9.5
amdinfer.libs/libssl-2a05fddd.so.3
amdinfer.libs/libamdinfer-5a411807.so.0.4.0
amdinfer.libs/libcrypto-7bcb84b6.so.3
amdinfer.libs/libopencv_imgproc4-8bcbd0cc.so.4.7.0
amdinfer.libs/libjpeg-fa415161.so.62.3.0
amdinfer.libs/libb64-593b3602.so
amdinfer.libs/libtrantor-e05c0da1.so.1.5.11
amdinfer.libs/libspdlog-69f02382.so.1.11.0
amdinfer.libs/libbrotlidec-8ea32250.so.1.0.9
amdinfer.libs/libopencv_imgcodecs4-30de4fcb.so.4.7.0
amdinfer.libs/libefsw-40c22a0e.so
