Metadata-Version: 2.1
Name: amdinfer
Version: 0.4.0
Summary: Python client library for the AMD Inference Server: unified inference across AMD CPUs, GPUs, and FPGAs
Home-page: https://github.com/Xilinx/inference-server
Author: Varun Sharma
Author-email: varun.sharma@amd.com
License: Apache 2.0
Project-URL: Bug Tracker, https://github.com/Xilinx/inference-server/issues
Project-URL: Changelog, https://xilinx.github.io/inference-server/main/changelog.html
Project-URL: Documentation, https://xilinx.github.io/inference-server/main/index.html
Project-URL: Source Code, https://github.com/Xilinx/inference-server
Classifier: Development Status :: 4 - Beta
Classifier: Intended Audience :: Science/Research
Classifier: Intended Audience :: Developers
Classifier: License :: OSI Approved :: Apache Software License
Classifier: Natural Language :: English
Classifier: Operating System :: POSIX :: Linux
Classifier: Programming Language :: C++
Classifier: Programming Language :: Python
Classifier: Programming Language :: Python :: 3
Classifier: Programming Language :: Python :: 3 :: Only
Classifier: Programming Language :: Python :: 3.6
Classifier: Programming Language :: Python :: 3.7
Classifier: Programming Language :: Python :: 3.8
Classifier: Programming Language :: Python :: 3.9
Classifier: Programming Language :: Python :: 3.10
Classifier: Programming Language :: Python :: Implementation :: CPython
Classifier: Topic :: Scientific/Engineering
Classifier: Topic :: Scientific/Engineering :: Artificial Intelligence
Classifier: Topic :: Scientific/Engineering :: Image Processing
Classifier: Topic :: Scientific/Engineering :: Image Recognition
Requires-Python: >=3.6
License-File: LICENSE
Requires-Dist: numpy
Requires-Dist: opencv-python-headless
